l2q/__init__.py
l2q/__main__.py
l2q/query_builder.py
l2q/test.py
l2q-0.1.dist-info/LICENSE
l2q-0.1.dist-info/METADATA
l2q-0.1.dist-info/WHEEL
l2q-0.1.dist-info/entry_points.txt
l2q-0.1.dist-info/top_level.txt
l2q-0.1.dist-info/RECORD
