Metadata-Version: 2.1
Name: l2q
Version: 0.1
Summary: UNKNOWN
Home-page: http://github.com/samuar/l2q
Author: Sam Holland
Author-email: sam.h@xewli.com
License: GPLv3+
Keywords: query builder
Platform: linux
Platform: mac
Classifier: License :: OSI Approved :: GNU General Public License v3 or later (GPLv3+)
Classifier: Operating System :: POSIX :: Linux
Classifier: Programming Language :: Python :: 3
Requires-Dist: numpy
